<?xml version="1.0" encoding="UTF-8"?>
<Entities
 build="b557"
 majorVersion="8"
 minorVersion="2"
 modelPersistenceProviderPackage="PostgresPersistenceProviderPackage"
 revision="7"
 schemaVersion="1020"
 universal="">
    <DataShapes>
        <DataShape
         aspect.isExtension="true"
         baseDataShape=""
         description=""
         documentationContent="&lt;p&gt;&lt;br&gt;&lt;/p&gt; "
         homeMashup=""
         lastModifiedDate="2018-10-24T21:00:18.106Z"
         name="SCM.API.DataShape.Package"
         projectName=""
         tags="Applications:RSM;Applications:SCM;TWUTL:RemoteServices">
            <avatar></avatar>
            <DesignTimePermissions>
                <Create></Create>
                <Read></Read>
                <Update></Update>
                <Delete></Delete>
                <Metadata></Metadata>
            </DesignTimePermissions>
            <RunTimePermissions></RunTimePermissions>
            <VisibilityPermissions>
                <Visibility></Visibility>
            </VisibilityPermissions>
            <ConfigurationTables></ConfigurationTables>
            <FieldDefinitions>
                <FieldDefinition
                 baseType="STRING"
                 description=""
                 name="ApprovalService"
                 ordinal="5"></FieldDefinition>
                <FieldDefinition
                 baseType="USERNAME"
                 description=""
                 name="CreatedBy"
                 ordinal="9"></FieldDefinition>
                <FieldDefinition
                 baseType="DATETIME"
                 description=""
                 name="DateCreated"
                 ordinal="16"></FieldDefinition>
                <FieldDefinition
                 baseType="STRING"
                 description=""
                 name="Description"
                 ordinal="8"></FieldDefinition>
                <FieldDefinition
                 baseType="DATETIME"
                 description=""
                 name="ExpirationDate"
                 ordinal="14"></FieldDefinition>
                <FieldDefinition
                 baseType="STRING"
                 description=""
                 name="Name"
                 ordinal="6"></FieldDefinition>
                <FieldDefinition
                 aspect.isPrimaryKey="true"
                 baseType="STRING"
                 description="Unique ID for the software update package"
                 name="PackageID"
                 ordinal="3"></FieldDefinition>
                <FieldDefinition
                 baseType="BOOLEAN"
                 description=""
                 name="Published"
                 ordinal="15"></FieldDefinition>
                <FieldDefinition
                 baseType="STRING"
                 description="Name of the File Repository that contains the software update package"
                 name="Repository"
                 ordinal="1"></FieldDefinition>
                <FieldDefinition
                 baseType="STRING"
                 description="Path of the file that contains the software update package"
                 name="RepositoryFilePath"
                 ordinal="2"></FieldDefinition>
                <FieldDefinition
                 aspect.defaultValue="true"
                 baseType="BOOLEAN"
                 description=""
                 name="RequiresApproval"
                 ordinal="4"></FieldDefinition>
                <FieldDefinition
                 baseType="STRING"
                 description=""
                 name="ScriptName"
                 ordinal="7"></FieldDefinition>
                <FieldDefinition
                 baseType="BOOLEAN"
                 description="Use CDN if available"
                 name="UseCdn"
                 ordinal="18"></FieldDefinition>
                <FieldDefinition
                 baseType="STRING"
                 description=""
                 name="Version1"
                 ordinal="10"></FieldDefinition>
                <FieldDefinition
                 baseType="STRING"
                 description=""
                 name="Version2"
                 ordinal="11"></FieldDefinition>
                <FieldDefinition
                 baseType="STRING"
                 description=""
                 name="Version3"
                 ordinal="12"></FieldDefinition>
                <FieldDefinition
                 baseType="STRING"
                 description=""
                 name="Version4"
                 ordinal="13"></FieldDefinition>
                <FieldDefinition
                 baseType="STRING"
                 description=""
                 name="VersionConcat"
                 ordinal="17"></FieldDefinition>
            </FieldDefinitions>
        </DataShape>
    </DataShapes>
</Entities>
