<?xml version="1.0" encoding="UTF-8"?>
<Entities
 build="b557"
 majorVersion="8"
 minorVersion="2"
 modelPersistenceProviderPackage="PostgresPersistenceProviderPackage"
 revision="7"
 schemaVersion="1020"
 universal="">
    <ThingShapes>
        <ThingShape
         className=""
         description="Shape to get Cradle information in JSON format under property -&#xA;1) CRADLEINFO"
         documentationContent="&lt;p&gt;Shape to get Cradle information in JSON format under property -&lt;br&gt;1) CRADLEINFO&lt;/p&gt;"
         homeMashup=""
         lastModifiedDate="2018-11-06T02:37:23.448Z"
         name="NCR.CRADLEts"
         projectName="DCS. Project.Main"
         tags="">
            <PropertyDefinitions>
                <PropertyDefinition
                 aspect.cacheTime="0.0"
                 aspect.dataChangeType="VALUE"
                 aspect.isLogged="true"
                 aspect.isPersistent="true"
                 aspect.isReadOnly="false"
                 baseType="STRING"
                 category="Cradle"
                 description="CRADLE INFO with JSON value"
                 isLocalOnly="false"
                 name="CRADLEINFO"
                 ordinal="1"></PropertyDefinition>
            </PropertyDefinitions>
            <ServiceDefinitions></ServiceDefinitions>
            <EventDefinitions></EventDefinitions>
            <ServiceMappings></ServiceMappings>
            <ServiceImplementations></ServiceImplementations>
            <Subscriptions></Subscriptions>
            <avatar></avatar>
            <DesignTimePermissions>
                <Create></Create>
                <Read></Read>
                <Update></Update>
                <Delete></Delete>
                <Metadata></Metadata>
            </DesignTimePermissions>
            <RunTimePermissions></RunTimePermissions>
            <VisibilityPermissions>
                <Visibility></Visibility>
            </VisibilityPermissions>
            <ConfigurationTables></ConfigurationTables>
            <PropertyBindings></PropertyBindings>
            <RemotePropertyBindings>
                <RemotePropertyBinding
                 aspect.startType="useDefaultValue"
                 foldType="NONE"
                 name="CRADLEINFO"
                 pushThreshold="0.0"
                 pushType="VALUE"
                 sourceName="CRADLEINFO"
                 timeout="0"></RemotePropertyBinding>
            </RemotePropertyBindings>
            <RemoteServiceBindings></RemoteServiceBindings>
            <RemoteEventBindings></RemoteEventBindings>
            <AlertConfigurations>
                <AlertDefinitions
                 name="CRADLEINFO"></AlertDefinitions>
            </AlertConfigurations>
            <InstanceRunTimePermissions></InstanceRunTimePermissions>
        </ThingShape>
    </ThingShapes>
</Entities>
